{"id":3351,"fields":[{"id":"0","t":"A","n":"aCat","cc":""},{"v":"Avian Bird Funk","t":"T","n":"tCat"},{"id":"1","t":"A","n":"aIntro","cc":""},{"v":"true","t":"B","n":"bIntro"},{"id":"-1","t":"A","n":"aIntro2","cc":""},{"v":"false","t":"B","n":"bIntro2"},{"v":"NONE","t":"T","n":"tBumper"},{"v":"Before","t":"T","n":"tBumperPlacement"},{"id":"2","t":"A","cues":[{"time":"S+0.00","n":"cQ1"}],"n":"aQuestion","cc":""},{"v":"If George Clinton wanted to incorporate a \u201cparliament\u201d of birds into his live show, what would be featured on stage?","t":"T","n":"tQ1"},{"id":"4","t":"A","n":"aChoices","cc":""},{"v":"funkadelic owls","t":"T","n":"tRight"},{"id":"6","t":"A","n":"aExp","cc":""},{"id":"7","t":"A","n":"aJoke","cc":""},{"v":"funkadelic turkeys","t":"T","n":"tW1"},{"v":"funkadelic eagles","t":"T","n":"tW2"},{"v":"funkadelic crows","t":"T","n":"tW3"},{"id":"9","t":"A","n":"aW1","cc":""},{"id":"11","t":"A","n":"aW2","cc":""},{"id":"13","t":"A","n":"aW3","cc":""},{"id":"-1","t":"A","n":"aWP1","cc":""},{"v":"false","t":"B","n":"bWP1"},{"id":"-1","t":"A","n":"aWP2","cc":""},{"v":"false","t":"B","n":"bWP2"},{"id":"-1","t":"A","n":"aWP3","cc":""},{"v":"false","t":"B","n":"bWP3"},{"v":"2,1,0","t":"T","n":"tWrongOrder"},{"v":"3,0,1,2","t":"T","n":"tMCOrder"},{"v":"3","t":"N","n":"nPrize"},{"id":"17","t":"A","n":"aPrizePre","cc":""},{"id":"18","t":"A","n":"aPrize","cc":""},{"v":"false","t":"B","n":"bNotLast1"},{"v":"false","t":"B","n":"bNotLast2"},{"v":"false","t":"B","n":"bNotLast3"},{"v":"Animals","t":"T","n":"tSubject"}]}