{"id":4431,"fields":[{"v":"All the Married Ladies","t":"T","n":"tCat"},{"id":"0","t":"A","n":"aCat","cc":""},{"id":"3","t":"A","n":"aClue","cc":""},{"v":"syrup lady|cookie lady|Chicago fire lady |seasoning lady|<i>The Graduate</i> lady|Virginia Woolf\u2019s novel lady|Robin Williams as a lady","t":"T","n":"tQuestions"},{"v":"Mrs. Butterworth|Mrs. Fields|Mrs. O\u2019Leary|Mrs. Dash |Mrs. Robinson|Mrs. Dalloway |Mrs. Doubtfire","t":"T","n":"tMatches"},{"v":"Mrs. Oreo|Mrs. Cow|Mrs. Oregano|Mrs. Hoffman|Mrs. Stream of Consciousness|Mrs. Jumanji","t":"T","n":"tDecoyA"},{"v":"Mrs. Keebler Elf|Mrs. Lantern |Mrs. Pinch|Mrs. Garfunkel|Mrs. Confusing|Robin Williams ","t":"T","n":"tDecoyB"},{"v":"Ms. Pacman |Ms. Marvel |Mr. Coffee|Mrs. Roosevelt|Mississippi River|Mrs. T|Mrs. USA|a \u201cMrs. Timberlake\u201d t-shirt|Dr. Quinn ","t":"T","n":"tDecoyGen"},{"id":"33","t":"A","n":"aETerrible","cc":""},{"id":"34","t":"A","n":"aEPerfectNeg","cc":""},{"id":"35","t":"A","n":"aEPerfectPos","cc":""},{"id":"36","t":"A","n":"aEVeryNeg","cc":""},{"id":"37","t":"A","n":"aENeg","cc":""},{"id":"38","t":"A","n":"aEBarelyPos","cc":""},{"id":"39","t":"A","n":"aEDecent","cc":""},{"id":"40","t":"A","n":"aEAwesome","cc":""},{"id":"-1","t":"A","n":"aEMultiplayer","cc":""}]}